restaround/__init__.py
restaround/restaround.py
restaround-0.1.4.dist-info/LICENSE
restaround-0.1.4.dist-info/METADATA
restaround-0.1.4.dist-info/WHEEL
restaround-0.1.4.dist-info/entry_points.txt
restaround-0.1.4.dist-info/top_level.txt
restaround-0.1.4.dist-info/RECORD
